{
    "users": [
        {
            "uuid": "c9d7dff4-d613-4dad-bb41-e1fb1913ccb7",
            "username": "sdindl",
            "email": "sdindl@sc.email.edu",
            "displayName": "Steven",
            "password": "Password2024",
            "progressTrackers": [
                {
                    "language": "filipino",
                    "completedGames": [
                        "easy-colorsGame",
                        "medium-storiesGame"
                    ]
                },
                {
                    "language": "",
                    "completedGames": []
                }
            ]
        }
    ]
}

